dropduplicatesplanb/README.MD
dropduplicatesplanb/__init__.py
dropduplicatesplanb/requirements.txt
dropduplicatesplanb/thirdparty.json
dropduplicatesplanb-0.11.dist-info/LICENSE.rst
dropduplicatesplanb-0.11.dist-info/METADATA
dropduplicatesplanb-0.11.dist-info/WHEEL
dropduplicatesplanb-0.11.dist-info/top_level.txt
dropduplicatesplanb-0.11.dist-info/RECORD
