Metadata-Version: 2.1
Name: dropduplicatesplanb
Version: 0.11
Summary: Drops duplicates in DataFrames with tedious dtypes
Home-page: https://github.com/hansalemaos/dropduplicatesplanb
Author: Johannes Fischer
Author-email: aulasparticularesdealemaosp@gmail.com
License: MIT
Keywords: dataframe,duplicates
Classifier: Development Status :: 4 - Beta
Classifier: Programming Language :: Python :: 3 :: Only
Classifier: Programming Language :: Python :: 3.10
Classifier: Topic :: Software Development :: Libraries :: Python Modules
Classifier: Topic :: Utilities
License-File: LICENSE.rst
Requires-Dist: arrayhascher
Requires-Dist: numpy
Requires-Dist: pandas
